[
  {
    "title": "The Launcher!",
    "date": "4/11/2025",
    "content": "The looong awaited launcher has finally released! Now making the installation of Taplixic even easier!",
    "image": "https://raw.githubusercontent.com/ArthurLumertz/taplixic-launcher/main/news/icon.png"
  },
  {
    "title": "The Laauncher!",
    "date": "4/11/20a25",
    "content": "The loaoong awaited launcher has finally released! Now making the installation of Taplixic even easier!",
    "image": "https://raw.githubusercontent.com/ArthurLumertz/taplixic-launcher/main/news/icon.png"
  }
]
